lucidicai/__init__.py
lucidicai/action.py
lucidicai/client.py
lucidicai/constants.py
lucidicai/context.py
lucidicai/dataset.py
lucidicai/decorators.py
lucidicai/errors.py
lucidicai/event.py
lucidicai/event_queue.py
lucidicai/feature_flag.py
lucidicai/image_upload.py
lucidicai/lru.py
lucidicai/model_pricing.py
lucidicai/session.py
lucidicai/session_obj.py
lucidicai/singleton.py
lucidicai/state.py
lucidicai/step.py
lucidicai/streaming.py
lucidicai/api/__init__.py
lucidicai/api/client.py
lucidicai/api/resources/__init__.py
lucidicai/api/resources/dataset.py
lucidicai/api/resources/evals.py
lucidicai/api/resources/event.py
lucidicai/api/resources/experiment.py
lucidicai/api/resources/feature_flag.py
lucidicai/api/resources/prompt.py
lucidicai/api/resources/session.py
lucidicai/core/__init__.py
lucidicai/core/config.py
lucidicai/core/errors.py
lucidicai/core/types.py
lucidicai/integrations/__init__.py
lucidicai/integrations/livekit.py
lucidicai/providers/__init__.py
lucidicai/providers/anthropic_handler.py
lucidicai/providers/base_providers.py
lucidicai/providers/image_storage.py
lucidicai/providers/langchain.py
lucidicai/providers/lucidic_exporter.py
lucidicai/providers/lucidic_span_processor.py
lucidicai/providers/openai_agents_handler.py
lucidicai/providers/openai_agents_instrumentor.py
lucidicai/providers/openai_handler.py
lucidicai/providers/opentelemetry_converter.py
lucidicai/providers/otel_handlers.py
lucidicai/providers/otel_init.py
lucidicai/providers/otel_provider.py
lucidicai/providers/pydantic_ai_handler.py
lucidicai/providers/text_storage.py
lucidicai/providers/universal_image_interceptor.py
lucidicai/sdk/__init__.py
lucidicai/sdk/bound_decorators.py
lucidicai/sdk/context.py
lucidicai/sdk/decorators.py
lucidicai/sdk/error_boundary.py
lucidicai/sdk/event.py
lucidicai/sdk/event_builder.py
lucidicai/sdk/init.py
lucidicai/sdk/session.py
lucidicai/sdk/shutdown_manager.py
lucidicai/sdk/features/__init__.py
lucidicai/sdk/features/dataset.py
lucidicai-3.4.1.dist-info/METADATA
lucidicai-3.4.1.dist-info/WHEEL
lucidicai-3.4.1.dist-info/top_level.txt
lucidicai-3.4.1.dist-info/RECORD
