Metadata-Version: 2.1
Name: lucidicai
Version: 3.4.1
Summary: Lucidic AI Python SDK
Author: Andy Liang
Author-email: andy@lucidic.ai
Classifier: Programming Language :: Python :: 3
Classifier: License :: OSI Approved :: MIT License
Classifier: Operating System :: OS Independent
Requires-Python: >=3.6
Requires-Dist: requests >=2.25.1
Requires-Dist: urllib3
Requires-Dist: boto3
Requires-Dist: python-dotenv
Requires-Dist: langchain
Requires-Dist: langchain-community
Requires-Dist: langchain-core
Requires-Dist: openai >=1.3.0
Requires-Dist: pillow
Requires-Dist: anthropic
Requires-Dist: opentelemetry-api
Requires-Dist: opentelemetry-sdk
Requires-Dist: opentelemetry-instrumentation
Requires-Dist: opentelemetry-instrumentation-openai
Requires-Dist: opentelemetry-instrumentation-anthropic
Requires-Dist: opentelemetry-instrumentation-langchain
Requires-Dist: opentelemetry-semantic-conventions-ai
